{
  "fundName": "הפניקס פנסיה מקיפה עוקב מדדים גמיש",
  "trackId": "14286",
  "totalAssetsBN": 0.1,
  "formattedTotalAssets": "101.78M",
  "assetClasses": [
    {
      "name": "Cash & Equivalents",
      "value": 0.0569,
      "formattedValue": "56.89M",
      "percentage": 55.89
    },
    {
      "name": "Stocks",
      "value": 0.0218,
      "formattedValue": "21.81M",
      "percentage": 21.43
    },
    {
      "name": "Non-Tradable Bonds",
      "value": 0.015,
      "formattedValue": "14.99M",
      "percentage": 14.73
    },
    {
      "name": "Bonds",
      "value": 0.007,
      "formattedValue": "7.01M",
      "percentage": 6.89
    },
    {
      "name": "Derivatives",
      "value": 0.0011,
      "formattedValue": "1.08M",
      "percentage": 1.06
    },
    {
      "name": "Futures",
      "value": -0.0,
      "formattedValue": "-4.68K",
      "percentage": -0.0
    }
  ],
  "breakdown": {
    "Non-Tradable Bonds": [
      {
        "subclass": "General",
        "value": 0.015,
        "formattedValue": "14.99M",
        "percentageOfClass": 100.0,
        "itemCount": 17,
        "totalPages": 2,
        "holdingsPages": [
          [
            {
              "name": "ערד 2035 סדרה 8892",
              "value": 0.0021,
              "formattedValue": "2.08M",
              "percentage": 13.9
            },
            {
              "name": "ערד 2034 סדרה 8880",
              "value": 0.002,
              "formattedValue": "1.96M",
              "percentage": 13.1
            },
            {
              "name": "ערד 2035 סדרה 8888",
              "value": 0.0019,
              "formattedValue": "1.88M",
              "percentage": 12.55
            },
            {
              "name": "ערד 2037 סדרה 8905",
              "value": 0.0016,
              "formattedValue": "1.57M",
              "percentage": 10.45
            },
            {
              "name": "ערד 2035 סדרה 8889",
              "value": 0.0012,
              "formattedValue": "1.22M",
              "percentage": 8.16
            },
            {
              "name": "ערד 2027 סדרה 8794",
              "value": 0.0012,
              "formattedValue": "1.19M",
              "percentage": 7.92
            },
            {
              "name": "ערד 2037 סדרה 8908",
              "value": 0.001,
              "formattedValue": "1.04M",
              "percentage": 6.92
            },
            {
              "name": "ערד 2028 סדרה 8798",
              "value": 0.0007,
              "formattedValue": "711.38K",
              "percentage": 4.75
            },
            {
              "name": "ערד 2031 סדרה 8841",
              "value": 0.0006,
              "formattedValue": "574.51K",
              "percentage": 3.83
            },
            {
              "name": "ערד 2032 סדרה 8846",
              "value": 0.0005,
              "formattedValue": "548.63K",
              "percentage": 3.66
            }
          ],
          [
            {
              "name": "ערד 2034סדרה 8879",
              "value": 0.0005,
              "formattedValue": "548.18K",
              "percentage": 3.66
            },
            {
              "name": "ערד 2037 סדרה 8912",
              "value": 0.0004,
              "formattedValue": "444.78K",
              "percentage": 2.97
            },
            {
              "name": "ערד 2030 סדרה 8825",
              "value": 0.0004,
              "formattedValue": "433.61K",
              "percentage": 2.89
            },
            {
              "name": "ערד 2037 סדרה 8911",
              "value": 0.0004,
              "formattedValue": "360.25K",
              "percentage": 2.4
            },
            {
              "name": "ערד 2036 סדרה 8901",
              "value": 0.0002,
              "formattedValue": "185.48K",
              "percentage": 1.24
            },
            {
              "name": "ערד 2036 סדרה 8896",
              "value": 0.0002,
              "formattedValue": "168.30K",
              "percentage": 1.12
            },
            {
              "name": "ערד 2033 סדרה 8869",
              "value": 0.0001,
              "formattedValue": "74.48K",
              "percentage": 0.5
            }
          ]
        ]
      }
    ],
    "Cash & Equivalents": [
      {
        "subclass": "Cash",
        "value": 0.0569,
        "formattedValue": "56.89M",
        "percentageOfClass": 100.0,
        "itemCount": 3,
        "totalPages": 1,
        "holdingsPages": [
          [
            {
              "name": "בנק הפועלים",
              "value": 0.0242,
              "formattedValue": "24.19M",
              "percentage": 42.52
            },
            {
              "name": "בנק לאומי",
              "value": 0.0203,
              "formattedValue": "20.33M",
              "percentage": 35.73
            },
            {
              "name": "בנק מזרחי",
              "value": 0.0124,
              "formattedValue": "12.37M",
              "percentage": 21.75
            }
          ]
        ]
      }
    ],
    "Bonds": [
      {
        "subclass": "ETFs",
        "value": 0.0066,
        "formattedValue": "6.61M",
        "percentageOfClass": 94.29,
        "itemCount": 5,
        "totalPages": 1,
        "holdingsPages": [
          [
            {
              "name": "iShares iBoxx $ Investment Gra",
              "value": 0.0031,
              "formattedValue": "3.09M",
              "percentage": 46.8
            },
            {
              "name": "SPDR Bloomberg Emerging Market",
              "value": 0.0021,
              "formattedValue": "2.08M",
              "percentage": 31.43
            },
            {
              "name": "Vanguard Intermediate-Term Tre",
              "value": 0.0007,
              "formattedValue": "722.39K",
              "percentage": 10.93
            },
            {
              "name": "iShares 7-10 Year Treasury Bon",
              "value": 0.0007,
              "formattedValue": "717.52K",
              "percentage": 10.85
            },
            {
              "name": "iShares USD High Yield Corp Bo",
              "value": 0.0,
              "formattedValue": "0.01K",
              "percentage": 0.0
            }
          ]
        ]
      },
      {
        "subclass": "Government Bonds",
        "value": 0.0004,
        "formattedValue": "400.38K",
        "percentageOfClass": 5.71,
        "itemCount": 1,
        "totalPages": 1,
        "holdingsPages": [
          [
            {
              "name": "B 0 08/06/26",
              "value": 0.0004,
              "formattedValue": "400.38K",
              "percentage": 100.0
            }
          ]
        ]
      }
    ],
    "Stocks": [
      {
        "subclass": "ETFs",
        "value": 0.0218,
        "formattedValue": "21.81M",
        "percentageOfClass": 100.0,
        "itemCount": 7,
        "totalPages": 1,
        "holdingsPages": [
          [
            {
              "name": "Amundi Nasdaq-100 II UCITS ETF",
              "value": 0.0072,
              "formattedValue": "7.23M",
              "percentage": 33.14
            },
            {
              "name": "SDJ600 GY",
              "value": 0.0048,
              "formattedValue": "4.76M",
              "percentage": 21.83
            },
            {
              "name": "Amundi MSCI Emerging Markets I",
              "value": 0.0027,
              "formattedValue": "2.66M",
              "percentage": 12.19
            },
            {
              "name": "NEXT FUNDS TOPIX Exchange Trad",
              "value": 0.0026,
              "formattedValue": "2.55M",
              "percentage": 11.7
            },
            {
              "name": "Amundi S&P 500 II UCITS ETF",
              "value": 0.0022,
              "formattedValue": "2.17M",
              "percentage": 9.94
            },
            {
              "name": "Invesco STOXX Europe 600 UCITS",
              "value": 0.0021,
              "formattedValue": "2.07M",
              "percentage": 9.48
            },
            {
              "name": "Amundi Index MSCI Emerging Mar",
              "value": 0.0004,
              "formattedValue": "375.26K",
              "percentage": 1.72
            }
          ]
        ]
      }
    ],
    "Derivatives": [
      {
        "subclass": "General",
        "value": 0.0011,
        "formattedValue": "1.08M",
        "percentageOfClass": 100.0,
        "itemCount": 9,
        "totalPages": 1,
        "holdingsPages": [
          [
            {
              "name": "SPTR INDEX",
              "value": 0.001,
              "formattedValue": "1.03M",
              "percentage": 95.24
            },
            {
              "name": "IBOXHY INDEX",
              "value": 0.0006,
              "formattedValue": "601.80K",
              "percentage": 55.77
            },
            {
              "name": "NDUEEGF INDEX",
              "value": 0.0003,
              "formattedValue": "277.66K",
              "percentage": 25.73
            },
            {
              "name": "EURILS",
              "value": 0.0,
              "formattedValue": "0.99K",
              "percentage": 0.09
            },
            {
              "name": "JPYILS",
              "value": 0.0,
              "formattedValue": "0.62K",
              "percentage": 0.06
            },
            {
              "name": "JCMDCOMP INDEX",
              "value": -0.0,
              "formattedValue": "-5.53K",
              "percentage": -0.51
            },
            {
              "name": "IBXXC1D1 INDEX",
              "value": -0.0,
              "formattedValue": "-17.42K",
              "percentage": -1.61
            },
            {
              "name": "IBOXIG INDEX",
              "value": -0.0,
              "formattedValue": "-21.61K",
              "percentage": -2.0
            },
            {
              "name": "USDILS",
              "value": -0.0008,
              "formattedValue": "-785.15K",
              "percentage": -72.76
            }
          ]
        ]
      }
    ],
    "Futures": [
      {
        "subclass": "General",
        "value": -0.0,
        "formattedValue": "-4.68K",
        "percentageOfClass": 100.0,
        "itemCount": 4,
        "totalPages": 1,
        "holdingsPages": [
          [
            {
              "name": "NASDAQ 100 STOCK INDX",
              "value": 0.0,
              "formattedValue": "21.47K",
              "percentage": -458.88
            },
            {
              "name": "TOPIX INDEX (TOKYO)",
              "value": 0.0,
              "formattedValue": "2.93K",
              "percentage": -62.53
            },
            {
              "name": "SXXP INDEX",
              "value": 0.0,
              "formattedValue": "0.65K",
              "percentage": -13.93
            },
            {
              "name": "MINI S&P500 INDEX",
              "value": -0.0,
              "formattedValue": "-29.72K",
              "percentage": 635.35
            }
          ]
        ]
      }
    ]
  }
}