{
  "fundName": " 驻住 住  拽 拽爪 拽",
  "trackId": "9650",
  "totalAssetsBN": 0.0,
  "formattedTotalAssets": "3.70M",
  "assetClasses": [
    {
      "name": "Bonds",
      "value": 0.0037,
      "formattedValue": "3.71M",
      "percentage": 100.17
    },
    {
      "name": "Other Assets",
      "value": -0.0,
      "formattedValue": "-6.18K",
      "percentage": -0.17
    }
  ],
  "breakdown": {
    "Other Assets": [
      {
        "subclass": "General",
        "value": -0.0,
        "formattedValue": "-6.18K",
        "percentageOfClass": 100.0,
        "itemCount": 1,
        "totalPages": 1,
        "holdingsPages": [
          [
            {
              "name": "  转驻注",
              "value": -0.0,
              "formattedValue": "-6.18K",
              "percentage": 100.0,
              "countryEmoji": ""
            }
          ]
        ]
      }
    ],
    "Bonds": [
      {
        "subclass": "Government Bonds",
        "value": 0.0026,
        "formattedValue": "2.57M",
        "percentageOfClass": 69.45,
        "itemCount": 2,
        "totalPages": 1,
        "holdingsPages": [
          [
            {
              "name": "爪 0841",
              "value": 0.002,
              "formattedValue": "1.99M",
              "percentage": 77.48,
              "countryEmoji": ""
            },
            {
              "name": "爪 1033",
              "value": 0.0006,
              "formattedValue": "579.70K",
              "percentage": 22.52,
              "countryEmoji": ""
            }
          ]
        ]
      },
      {
        "subclass": "Corporate Bonds",
        "value": 0.0011,
        "formattedValue": "1.13M",
        "percentageOfClass": 30.55,
        "itemCount": 9,
        "totalPages": 1,
        "holdingsPages": [
          [
            {
              "name": "专 驻转 驻拽转  68",
              "value": 0.0002,
              "formattedValue": "158.75K",
              "percentage": 14.02,
              "countryEmoji": ""
            },
            {
              "name": "  183",
              "value": 0.0002,
              "formattedValue": "157.34K",
              "percentage": 13.9,
              "countryEmoji": ""
            },
            {
              "name": "住拽   ",
              "value": 0.0002,
              "formattedValue": "156.09K",
              "percentage": 13.79,
              "countryEmoji": ""
            },
            {
              "name": "  186",
              "value": 0.0001,
              "formattedValue": "117.52K",
              "percentage": 10.38,
              "countryEmoji": ""
            },
            {
              "name": " 转 转转  405",
              "value": 0.0001,
              "formattedValue": "111.83K",
              "percentage": 9.88,
              "countryEmoji": ""
            },
            {
              "name": "住拽   ",
              "value": 0.0001,
              "formattedValue": "109.42K",
              "percentage": 9.66,
              "countryEmoji": ""
            },
            {
              "name": "住拽 驻 转  ",
              "value": 0.0001,
              "formattedValue": "109.04K",
              "percentage": 9.63,
              "countryEmoji": ""
            },
            {
              "name": "专 驻转 转转  71",
              "value": 0.0001,
              "formattedValue": "106.95K",
              "percentage": 9.45,
              "countryEmoji": ""
            },
            {
              "name": "专 驻转 驻  70",
              "value": 0.0001,
              "formattedValue": "105.34K",
              "percentage": 9.3,
              "countryEmoji": ""
            }
          ]
        ]
      }
    ]
  },
  "geoSunburst": [
    {
      "name": "Israel",
      "value": 0.0037,
      "formattedValue": "3.71M",
      "children": [
        {
          "name": "Bonds",
          "value": 0.0037,
          "formattedValue": "3.71M"
        }
      ]
    }
  ]
}