{
  "fundName": "砖专 砖 驻住 转 转",
  "trackId": "13211",
  "totalAssetsBN": 0.2,
  "formattedTotalAssets": "201.46M",
  "assetClasses": [
    {
      "name": "Stocks",
      "value": 0.0939,
      "formattedValue": "93.94M",
      "percentage": 46.63
    },
    {
      "name": "Bonds",
      "value": 0.0648,
      "formattedValue": "64.80M",
      "percentage": 32.17
    },
    {
      "name": "Cash & Equivalents",
      "value": 0.0297,
      "formattedValue": "29.73M",
      "percentage": 14.76
    },
    {
      "name": "Mutual Funds",
      "value": 0.0067,
      "formattedValue": "6.74M",
      "percentage": 3.35
    },
    {
      "name": "Investment Funds",
      "value": 0.0037,
      "formattedValue": "3.65M",
      "percentage": 1.81
    },
    {
      "name": "Derivatives",
      "value": 0.0017,
      "formattedValue": "1.75M",
      "percentage": 0.87
    },
    {
      "name": "Futures",
      "value": 0.0013,
      "formattedValue": "1.32M",
      "percentage": 0.66
    },
    {
      "name": "Non-Tradable Stocks",
      "value": 0.0007,
      "formattedValue": "718.71K",
      "percentage": 0.36
    },
    {
      "name": "Warrants",
      "value": 0.0001,
      "formattedValue": "77.80K",
      "percentage": 0.04
    },
    {
      "name": "Options",
      "value": -0.0003,
      "formattedValue": "-279.95K",
      "percentage": -0.14
    },
    {
      "name": "Other Assets",
      "value": -0.001,
      "formattedValue": "-991.11K",
      "percentage": -0.49
    }
  ],
  "breakdown": {
    "Non-Tradable Stocks": [
      {
        "subclass": "Direct Holdings",
        "value": 0.0007,
        "formattedValue": "718.71K",
        "percentageOfClass": 100.0,
        "itemCount": 1,
        "totalPages": 1,
        "holdingsPages": [
          [
            {
              "name": "驻.住..住 转 注\" (KSP)",
              "value": 0.0007,
              "formattedValue": "718.71K",
              "percentage": 100.0,
              "countryEmoji": ""
            }
          ]
        ]
      }
    ],
    "Cash & Equivalents": [
      {
        "subclass": "Cash",
        "value": 0.0297,
        "formattedValue": "29.73M",
        "percentageOfClass": 100.0,
        "itemCount": 7,
        "totalPages": 1,
        "holdingsPages": [
          [
            {
              "name": "",
              "value": 0.0256,
              "formattedValue": "25.61M",
              "percentage": 86.15,
              "countryEmoji": ""
            },
            {
              "name": "Goldman Sachs Group Inc",
              "value": 0.0052,
              "formattedValue": "5.21M",
              "percentage": 17.52,
              "countryEmoji": ""
            },
            {
              "name": "JP Morgan",
              "value": -0.0009,
              "formattedValue": "-882.01K",
              "percentage": -2.97,
              "countryEmoji": ""
            },
            {
              "name": "Citibank, NA",
              "value": -0.0003,
              "formattedValue": "-304.92K",
              "percentage": -1.03,
              "countryEmoji": ""
            },
            {
              "name": "驻注",
              "value": 0.0002,
              "formattedValue": "152.10K",
              "percentage": 0.51,
              "countryEmoji": ""
            },
            {
              "name": "住拽",
              "value": -0.0001,
              "formattedValue": "-88.07K",
              "percentage": -0.3,
              "countryEmoji": ""
            },
            {
              "name": "Signature Bank/New York NY",
              "value": 0.0,
              "formattedValue": "32.81K",
              "percentage": 0.11,
              "countryEmoji": ""
            }
          ]
        ]
      }
    ],
    "Other Assets": [
      {
        "subclass": "General",
        "value": -0.001,
        "formattedValue": "-991.11K",
        "percentageOfClass": 100.0,
        "itemCount": 3,
        "totalPages": 1,
        "holdingsPages": [
          [
            {
              "name": "转专转 /",
              "value": -0.0009,
              "formattedValue": "-934.93K",
              "percentage": 94.33,
              "countryEmoji": ""
            },
            {
              "name": "    驻拽",
              "value": -0.0,
              "formattedValue": "-35.08K",
              "percentage": 3.54,
              "countryEmoji": ""
            },
            {
              "name": "    爪专",
              "value": -0.0,
              "formattedValue": "-21.10K",
              "percentage": 2.13,
              "countryEmoji": ""
            }
          ]
        ]
      }
    ],
    "Bonds": [
      {
        "subclass": "Government Bonds",
        "value": 0.0648,
        "formattedValue": "64.80M",
        "percentageOfClass": 100.0,
        "itemCount": 18,
        "totalPages": 2,
        "holdingsPages": [
          [
            {
              "name": ".拽.. 116",
              "value": 0.0108,
              "formattedValue": "10.80M",
              "percentage": 16.66,
              "countryEmoji": ""
            },
            {
              "name": ".拽.. 416",
              "value": 0.0074,
              "formattedValue": "7.41M",
              "percentage": 11.44,
              "countryEmoji": ""
            },
            {
              "name": ".拽.. 1215",
              "value": 0.0061,
              "formattedValue": "6.13M",
              "percentage": 9.46,
              "countryEmoji": ""
            },
            {
              "name": ".拽.. 1016",
              "value": 0.0061,
              "formattedValue": "6.07M",
              "percentage": 9.37,
              "countryEmoji": ""
            },
            {
              "name": ".拽.. 616",
              "value": 0.0049,
              "formattedValue": "4.90M",
              "percentage": 7.55,
              "countryEmoji": ""
            },
            {
              "name": "B 11/25/25",
              "value": 0.0044,
              "formattedValue": "4.40M",
              "percentage": 6.79,
              "countryEmoji": "吼"
            },
            {
              "name": "B 11/13/25",
              "value": 0.0036,
              "formattedValue": "3.57M",
              "percentage": 5.51,
              "countryEmoji": "吼"
            },
            {
              "name": ".拽.. 1115",
              "value": 0.0034,
              "formattedValue": "3.43M",
              "percentage": 5.29,
              "countryEmoji": ""
            },
            {
              "name": "B 01/15/26",
              "value": 0.0033,
              "formattedValue": "3.30M",
              "percentage": 5.09,
              "countryEmoji": "吼"
            },
            {
              "name": ".拽. 216",
              "value": 0.0031,
              "formattedValue": "3.13M",
              "percentage": 4.84,
              "countryEmoji": ""
            }
          ],
          [
            {
              "name": ".拽.. 316",
              "value": 0.003,
              "formattedValue": "3.01M",
              "percentage": 4.65,
              "countryEmoji": ""
            },
            {
              "name": "B 10/28/25",
              "value": 0.0023,
              "formattedValue": "2.33M",
              "percentage": 3.59,
              "countryEmoji": "吼"
            },
            {
              "name": "B 10/21/25",
              "value": 0.0021,
              "formattedValue": "2.06M",
              "percentage": 3.18,
              "countryEmoji": "吼"
            },
            {
              "name": ".拽.. 1015",
              "value": 0.0019,
              "formattedValue": "1.91M",
              "percentage": 2.94,
              "countryEmoji": ""
            },
            {
              "name": ".拽.. 516",
              "value": 0.001,
              "formattedValue": "992.25K",
              "percentage": 1.53,
              "countryEmoji": ""
            },
            {
              "name": ".拽.. 916",
              "value": 0.0008,
              "formattedValue": "810.89K",
              "percentage": 1.25,
              "countryEmoji": ""
            },
            {
              "name": ".拽.. 726",
              "value": 0.0003,
              "formattedValue": "331.60K",
              "percentage": 0.51,
              "countryEmoji": ""
            },
            {
              "name": ".拽.. 816",
              "value": 0.0002,
              "formattedValue": "224.65K",
              "percentage": 0.35,
              "countryEmoji": ""
            }
          ]
        ]
      }
    ],
    "Options": [
      {
        "subclass": "Tradable",
        "value": -0.0001,
        "formattedValue": "-74.79K",
        "percentageOfClass": 26.72,
        "itemCount": 12,
        "totalPages": 2,
        "holdingsPages": [
          [
            {
              "name": "NASDAQ 100 E-MINI Dec24c",
              "value": -0.0002,
              "formattedValue": "-193.67K",
              "percentage": 258.95,
              "countryEmoji": ""
            },
            {
              "name": "S&P500 EMINI OPTN Oct25P",
              "value": 0.0002,
              "formattedValue": "168.90K",
              "percentage": -225.83,
              "countryEmoji": ""
            },
            {
              "name": "NKY 12/12/25 C45000",
              "value": -0.0002,
              "formattedValue": "-158.74K",
              "percentage": 212.25,
              "countryEmoji": ""
            },
            {
              "name": "NKY 12/12/25 C43000",
              "value": 0.0001,
              "formattedValue": "141.89K",
              "percentage": -189.72,
              "countryEmoji": ""
            },
            {
              "name": "S&P500 EMINI OPTN Dec25P",
              "value": 0.0001,
              "formattedValue": "120.30K",
              "percentage": -160.85,
              "countryEmoji": ""
            },
            {
              "name": "NKY 10/10/25 C43000",
              "value": 0.0001,
              "formattedValue": "103.55K",
              "percentage": -138.45,
              "countryEmoji": ""
            },
            {
              "name": "NASDAQ 100 E-MINI Dec24P",
              "value": -0.0001,
              "formattedValue": "-91.14K",
              "percentage": 121.86,
              "countryEmoji": ""
            },
            {
              "name": "WFC US 10/17/25 C80",
              "value": -0.0001,
              "formattedValue": "-72.02K",
              "percentage": 96.3,
              "countryEmoji": ""
            },
            {
              "name": "NKY 10/10/25 C44000",
              "value": -0.0001,
              "formattedValue": "-62.77K",
              "percentage": 83.92,
              "countryEmoji": ""
            },
            {
              "name": "NASD100 Min EOM O NOV25P",
              "value": -0.0001,
              "formattedValue": "-56.22K",
              "percentage": 75.17,
              "countryEmoji": ""
            }
          ],
          [
            {
              "name": "S&P500 EMINI OPTN Nov25P",
              "value": 0.0001,
              "formattedValue": "55.65K",
              "percentage": -74.41,
              "countryEmoji": ""
            },
            {
              "name": "NKY 10/10/25 C45000",
              "value": -0.0,
              "formattedValue": "-30.53K",
              "percentage": 40.82,
              "countryEmoji": ""
            }
          ]
        ]
      },
      {
        "subclass": "Non-Tradable",
        "value": -0.0002,
        "formattedValue": "-205.16K",
        "percentageOfClass": 73.28,
        "itemCount": 54,
        "totalPages": 6,
        "holdingsPages": [
          [
            {
              "name": "驻爪 住 专 砖拽 DISCOUNT P3.65 08/10/25",
              "value": 0.0005,
              "formattedValue": "500.92K",
              "percentage": -244.17,
              "countryEmoji": "吼"
            },
            {
              "name": "驻爪 住 专 砖拽 DISCOUNT P3.65 08/10/25 SELL",
              "value": -0.0005,
              "formattedValue": "-500.79K",
              "percentage": 244.1,
              "countryEmoji": "吼"
            },
            {
              "name": "驻爪 住 专 砖拽 DISCOUNT P3.55 08/10/25 BUY",
              "value": 0.0004,
              "formattedValue": "355.30K",
              "percentage": -173.19,
              "countryEmoji": "吼"
            },
            {
              "name": "驻爪 住 专 砖拽 DISCOUNT P3.55 08/10/25",
              "value": -0.0004,
              "formattedValue": "-355.16K",
              "percentage": 173.12,
              "countryEmoji": "吼"
            },
            {
              "name": "驻爪 住 专 砖拽 LEUMI P3.7 13/10/25 L",
              "value": 0.0003,
              "formattedValue": "286.67K",
              "percentage": -139.73,
              "countryEmoji": "吼"
            },
            {
              "name": "驻爪 住 专 砖拽 Leumi P3.7 13/10/25 S",
              "value": -0.0003,
              "formattedValue": "-286.56K",
              "percentage": 139.68,
              "countryEmoji": "吼"
            },
            {
              "name": "驻爪 住 专 砖拽 POALIM P3.6 06/10/25",
              "value": 0.0002,
              "formattedValue": "214.11K",
              "percentage": -104.37,
              "countryEmoji": "吼"
            },
            {
              "name": "驻爪 住 专 砖拽 POALIM P3.6 06/10/25 SELL",
              "value": -0.0002,
              "formattedValue": "-214.03K",
              "percentage": 104.32,
              "countryEmoji": "吼"
            },
            {
              "name": "驻爪 住 专 砖拽 Leumi P3.6 13/10/25 L",
              "value": 0.0002,
              "formattedValue": "213.91K",
              "percentage": -104.27,
              "countryEmoji": "吼"
            },
            {
              "name": "驻爪 住 专 砖拽 LEUMI P3.6 13/10/25 S",
              "value": -0.0002,
              "formattedValue": "-213.80K",
              "percentage": 104.21,
              "countryEmoji": "吼"
            }
          ],
          [
            {
              "name": "驻爪 住 专 砖拽 POALIM P3.5 06/10/25 BUY",
              "value": 0.0001,
              "formattedValue": "141.26K",
              "percentage": -68.86,
              "countryEmoji": "吼"
            },
            {
              "name": "驻爪 住 专 砖拽 POALIM P3.5 06/10/25",
              "value": -0.0001,
              "formattedValue": "-141.23K",
              "percentage": 68.84,
              "countryEmoji": "吼"
            },
            {
              "name": "驻爪 住 专 砖拽 DISCOUNT P3.4 26/11/25 SELL",
              "value": -0.0,
              "formattedValue": "-39.23K",
              "percentage": 19.12,
              "countryEmoji": "吼"
            },
            {
              "name": "驻爪 住 专 砖拽 POALIM P3.39 05/12/25 SELL",
              "value": -0.0,
              "formattedValue": "-37.49K",
              "percentage": 18.27,
              "countryEmoji": "吼"
            },
            {
              "name": "驻爪 住 专 砖拽 LEUMI P3.38 01/12/25 SELL",
              "value": -0.0,
              "formattedValue": "-34.18K",
              "percentage": 16.66,
              "countryEmoji": "吼"
            },
            {
              "name": "驻爪 住 专 砖拽 CITI P3.38 18/12/25 SELL",
              "value": -0.0,
              "formattedValue": "-33.80K",
              "percentage": 16.47,
              "countryEmoji": "吼"
            },
            {
              "name": "驻爪 住 专 砖拽 DISCOUNT C3.29 23/12/25 SELL",
              "value": -0.0,
              "formattedValue": "-24.31K",
              "percentage": 11.85,
              "countryEmoji": "吼"
            },
            {
              "name": "驻爪 住 专 砖拽 POALIM P3.25 26/03/26 SELL",
              "value": -0.0,
              "formattedValue": "-19.06K",
              "percentage": 9.29,
              "countryEmoji": "吼"
            },
            {
              "name": "驻爪 住 专 砖拽 DISCOUNT P3.25 24/03/26 SELL",
              "value": -0.0,
              "formattedValue": "-18.45K",
              "percentage": 9.0,
              "countryEmoji": "吼"
            },
            {
              "name": "驻爪 住 专 砖拽 DISCOUNT P3.29 23/12/25 SELL",
              "value": -0.0,
              "formattedValue": "-17.91K",
              "percentage": 8.73,
              "countryEmoji": "吼"
            }
          ],
          [
            {
              "name": "驻爪 住 专 砖拽 GS P3.9 03/10/25",
              "value": 0.0,
              "formattedValue": "16.02K",
              "percentage": -7.81,
              "countryEmoji": ""
            },
            {
              "name": "驻爪 住 专 砖拽 GS P3.9 03/10/25 SELL",
              "value": -0.0,
              "formattedValue": "-15.57K",
              "percentage": 7.59,
              "countryEmoji": ""
            },
            {
              "name": "驻爪 住 专 砖拽 CITI P3.22 06/03/26 SELL",
              "value": -0.0,
              "formattedValue": "-13.77K",
              "percentage": 6.71,
              "countryEmoji": "吼"
            },
            {
              "name": "驻爪 住 专 砖拽 POALIM C3.59 26/03/26 BUY",
              "value": 0.0,
              "formattedValue": "13.16K",
              "percentage": -6.42,
              "countryEmoji": "吼"
            },
            {
              "name": "驻爪 住 专 砖拽 DISCOUNT C3.575 12/03/26 BUY",
              "value": 0.0,
              "formattedValue": "12.73K",
              "percentage": -6.2,
              "countryEmoji": "吼"
            },
            {
              "name": "驻爪 住 专 砖拽 DISCOUNT P3.21 12/03/26 SELL",
              "value": -0.0,
              "formattedValue": "-12.64K",
              "percentage": 6.16,
              "countryEmoji": "吼"
            },
            {
              "name": "驻爪 住 专 砖拽 CITI C3.575 06/03/26 BUY",
              "value": 0.0,
              "formattedValue": "12.47K",
              "percentage": -6.08,
              "countryEmoji": "吼"
            },
            {
              "name": "驻爪 住 专 砖拽 DISCOUNT C3.6 24/03/26 BUY",
              "value": 0.0,
              "formattedValue": "11.60K",
              "percentage": -5.66,
              "countryEmoji": "吼"
            },
            {
              "name": "驻爪 住 专 砖拽 CITI C3.38 18/12/25 SELL",
              "value": -0.0,
              "formattedValue": "-9.38K",
              "percentage": 4.57,
              "countryEmoji": "吼"
            },
            {
              "name": "驻爪 住 GS C1,637.14 ESLT.TA 15/10/25 SELL",
              "value": -0.0,
              "formattedValue": "-8.36K",
              "percentage": 4.08,
              "countryEmoji": ""
            }
          ],
          [
            {
              "name": "驻爪 住 专 砖拽 LEUMI C3.39 05/12/25 SELL",
              "value": -0.0,
              "formattedValue": "-7.65K",
              "percentage": 3.73,
              "countryEmoji": "吼"
            },
            {
              "name": "驻爪 住 专 砖拽 LEUMI C3.38 01/12/25 SELL",
              "value": -0.0,
              "formattedValue": "-7.64K",
              "percentage": 3.72,
              "countryEmoji": "吼"
            },
            {
              "name": "驻爪 住 专 砖拽 DISCOUNT C3.55 13/01/26 BUY",
              "value": 0.0,
              "formattedValue": "6.43K",
              "percentage": -3.14,
              "countryEmoji": "吼"
            },
            {
              "name": "驻爪 住 专 砖拽 LEUMI C3.59 06/01/26 BUY",
              "value": 0.0,
              "formattedValue": "6.24K",
              "percentage": -3.04,
              "countryEmoji": "吼"
            },
            {
              "name": "驻爪 住 专 砖拽 LEUMI C3.60 07/01/26 BUY",
              "value": 0.0,
              "formattedValue": "5.85K",
              "percentage": -2.85,
              "countryEmoji": "吼"
            },
            {
              "name": "驻爪 住 专 砖拽 POALIM C3.5 05/12/25 BUY",
              "value": 0.0,
              "formattedValue": "5.60K",
              "percentage": -2.73,
              "countryEmoji": "吼"
            },
            {
              "name": "驻爪 住 专 砖拽 DISCOUNT C3.4 26/11/25 SELL",
              "value": -0.0,
              "formattedValue": "-5.58K",
              "percentage": 2.72,
              "countryEmoji": "吼"
            },
            {
              "name": "驻爪 住 专 砖拽 CITI C3.62 18/12/25 BUY",
              "value": 0.0,
              "formattedValue": "2.97K",
              "percentage": -1.45,
              "countryEmoji": "吼"
            },
            {
              "name": "驻爪 住 专 砖拽 CITI C3.60 18/12/25 BUY",
              "value": 0.0,
              "formattedValue": "2.12K",
              "percentage": -1.03,
              "countryEmoji": "吼"
            },
            {
              "name": "驻爪 住 专 砖拽 POALIM C3.6 05/12/25 BUY",
              "value": 0.0,
              "formattedValue": "1.96K",
              "percentage": -0.96,
              "countryEmoji": "吼"
            }
          ],
          [
            {
              "name": "驻爪 住 专 砖拽 DISCOUNT C3.58 23/12/25 BUY",
              "value": 0.0,
              "formattedValue": "1.73K",
              "percentage": -0.84,
              "countryEmoji": "吼"
            },
            {
              "name": "驻爪 住 专 砖拽 LEUMI C3.6 01/12/25 BUY",
              "value": 0.0,
              "formattedValue": "1.63K",
              "percentage": -0.8,
              "countryEmoji": "吼"
            },
            {
              "name": "驻爪 住 专 砖拽 POALIM C3.7 05/12/25 SELL 15/07",
              "value": -0.0,
              "formattedValue": "-0.67K",
              "percentage": 0.33,
              "countryEmoji": "吼"
            },
            {
              "name": "驻爪 住 专 砖拽 POALIM C3.7 05/12/25 SELL",
              "value": -0.0,
              "formattedValue": "-0.65K",
              "percentage": 0.31,
              "countryEmoji": "吼"
            },
            {
              "name": "驻爪 住 专 砖拽 CITI C3.75 18/12/25 BUY",
              "value": 0.0,
              "formattedValue": "0.53K",
              "percentage": -0.26,
              "countryEmoji": "吼"
            },
            {
              "name": "驻爪 住 专 砖拽 CITI C3.75 18/12/25 SELL",
              "value": -0.0,
              "formattedValue": "-0.51K",
              "percentage": 0.25,
              "countryEmoji": "吼"
            },
            {
              "name": "驻爪 住 专 砖拽 LEUMI C3.73 01/12/25 SELL",
              "value": -0.0,
              "formattedValue": "-0.35K",
              "percentage": 0.17,
              "countryEmoji": "吼"
            },
            {
              "name": "驻爪 住 专 砖拽 POALIM C3.70 05/12/25 BUY",
              "value": 0.0,
              "formattedValue": "0.22K",
              "percentage": -0.11,
              "countryEmoji": "吼"
            },
            {
              "name": "驻爪 住 专 砖拽 LEUMI C3.73 01/12/25 BUY",
              "value": 0.0,
              "formattedValue": "0.10K",
              "percentage": -0.05,
              "countryEmoji": "吼"
            },
            {
              "name": "驻爪 住 专 砖拽 DISCOUNT C3.75 26/11/25 BUY",
              "value": 0.0,
              "formattedValue": "0.04K",
              "percentage": -0.02,
              "countryEmoji": "吼"
            }
          ],
          [
            {
              "name": "驻爪 住 专 砖拽 GS C4.2 03/10/25",
              "value": -0.0,
              "formattedValue": "-0.00K",
              "percentage": 0.0,
              "countryEmoji": ""
            },
            {
              "name": "驻爪 住 专 砖拽 GS P3.7 03/10/25",
              "value": -0.0,
              "formattedValue": "-0.00K",
              "percentage": 0.0,
              "countryEmoji": ""
            },
            {
              "name": "驻爪 住 专 砖拽 GS P3.7 03/10/25 BUY",
              "value": 0.0,
              "formattedValue": "0.00K",
              "percentage": -0.0,
              "countryEmoji": ""
            },
            {
              "name": "驻爪 住 专 砖拽 GS C4.2 03/10/25 BUY",
              "value": 0.0,
              "formattedValue": "0.00K",
              "percentage": -0.0,
              "countryEmoji": ""
            }
          ]
        ]
      }
    ],
    "Stocks": [
      {
        "subclass": "Direct Holdings",
        "value": 0.0853,
        "formattedValue": "85.31M",
        "percentageOfClass": 90.82,
        "itemCount": 77,
        "totalPages": 8,
        "holdingsPages": [
          [
            {
              "name": "驻注",
              "value": 0.0086,
              "formattedValue": "8.60M",
              "percentage": 10.08,
              "countryEmoji": ""
            },
            {
              "name": "",
              "value": 0.0078,
              "formattedValue": "7.85M",
              "percentage": 9.2,
              "countryEmoji": ""
            },
            {
              "name": "Taiwan Semiconductor Manufactu",
              "value": 0.0048,
              "formattedValue": "4.77M",
              "percentage": 5.6,
              "countryEmoji": ""
            },
            {
              "name": "住拽 ",
              "value": 0.0041,
              "formattedValue": "4.07M",
              "percentage": 4.77,
              "countryEmoji": ""
            },
            {
              "name": "Amazon.com Inc",
              "value": 0.0041,
              "formattedValue": "4.05M",
              "percentage": 4.75,
              "countryEmoji": "吼"
            },
            {
              "name": "Alphabet Inc",
              "value": 0.0033,
              "formattedValue": "3.30M",
              "percentage": 3.87,
              "countryEmoji": "吼"
            },
            {
              "name": "Oracle Corp",
              "value": 0.0024,
              "formattedValue": "2.36M",
              "percentage": 2.77,
              "countryEmoji": "吼"
            },
            {
              "name": " 注专转",
              "value": 0.0022,
              "formattedValue": "2.21M",
              "percentage": 2.59,
              "countryEmoji": ""
            },
            {
              "name": "砖驻专住",
              "value": 0.0022,
              "formattedValue": "2.21M",
              "percentage": 2.59,
              "countryEmoji": ""
            },
            {
              "name": "Microsoft Corp",
              "value": 0.0022,
              "formattedValue": "2.19M",
              "percentage": 2.57,
              "countryEmoji": "吼"
            }
          ],
          [
            {
              "name": "Uber Technologies Inc",
              "value": 0.0019,
              "formattedValue": "1.91M",
              "percentage": 2.24,
              "countryEmoji": "吼"
            },
            {
              "name": "Cisco Systems Inc",
              "value": 0.0019,
              "formattedValue": "1.87M",
              "percentage": 2.19,
              "countryEmoji": "吼"
            },
            {
              "name": "Entegris Inc",
              "value": 0.0014,
              "formattedValue": "1.41M",
              "percentage": 1.66,
              "countryEmoji": "吼"
            },
            {
              "name": "Meta Platforms Inc",
              "value": 0.0014,
              "formattedValue": "1.37M",
              "percentage": 1.61,
              "countryEmoji": "吼"
            },
            {
              "name": "Expand Energy Corp",
              "value": 0.0014,
              "formattedValue": "1.36M",
              "percentage": 1.59,
              "countryEmoji": "吼"
            },
            {
              "name": "Intercontinental Exchange Inc",
              "value": 0.0013,
              "formattedValue": "1.33M",
              "percentage": 1.56,
              "countryEmoji": "吼"
            },
            {
              "name": "Zoom Video Communications Inc",
              "value": 0.0013,
              "formattedValue": "1.31M",
              "percentage": 1.54,
              "countryEmoji": "吼"
            },
            {
              "name": "LVMH Moet Hennessy Louis Vuitt",
              "value": 0.0013,
              "formattedValue": "1.28M",
              "percentage": 1.5,
              "countryEmoji": ""
            },
            {
              "name": "Wells Fargo & Co",
              "value": 0.0012,
              "formattedValue": "1.16M",
              "percentage": 1.36,
              "countryEmoji": "吼"
            },
            {
              "name": "CRH PLC",
              "value": 0.0011,
              "formattedValue": "1.13M",
              "percentage": 1.32,
              "countryEmoji": "吼"
            }
          ],
          [
            {
              "name": "驻转 拽驻",
              "value": 0.0011,
              "formattedValue": "1.10M",
              "percentage": 1.29,
              "countryEmoji": ""
            },
            {
              "name": "注",
              "value": 0.0011,
              "formattedValue": "1.10M",
              "percentage": 1.28,
              "countryEmoji": ""
            },
            {
              "name": "Komatsu Ltd",
              "value": 0.0011,
              "formattedValue": "1.08M",
              "percentage": 1.26,
              "countryEmoji": ""
            },
            {
              "name": " 专",
              "value": 0.0011,
              "formattedValue": "1.07M",
              "percentage": 1.26,
              "countryEmoji": ""
            },
            {
              "name": "Shell PLC",
              "value": 0.001,
              "formattedValue": "1.01M",
              "percentage": 1.18,
              "countryEmoji": ""
            },
            {
              "name": "Nutrien Ltd",
              "value": 0.001,
              "formattedValue": "1.01M",
              "percentage": 1.18,
              "countryEmoji": ""
            },
            {
              "name": "MongoDB Inc",
              "value": 0.001,
              "formattedValue": "998.58K",
              "percentage": 1.17,
              "countryEmoji": "吼"
            },
            {
              "name": "AppLovin Corp",
              "value": 0.001,
              "formattedValue": "994.39K",
              "percentage": 1.17,
              "countryEmoji": "吼"
            },
            {
              "name": "MercadoLibre Inc",
              "value": 0.001,
              "formattedValue": "977.41K",
              "percentage": 1.15,
              "countryEmoji": "吼"
            },
            {
              "name": "Palo Alto Networks Inc",
              "value": 0.0009,
              "formattedValue": "931.35K",
              "percentage": 1.09,
              "countryEmoji": "吼"
            }
          ],
          [
            {
              "name": "",
              "value": 0.0009,
              "formattedValue": "921.71K",
              "percentage": 1.08,
              "countryEmoji": ""
            },
            {
              "name": "Universal Music Group NV",
              "value": 0.0009,
              "formattedValue": "918.24K",
              "percentage": 1.08,
              "countryEmoji": "仇"
            },
            {
              "name": "专",
              "value": 0.0009,
              "formattedValue": "879.21K",
              "percentage": 1.03,
              "countryEmoji": ""
            },
            {
              "name": "Lyft Inc",
              "value": 0.0009,
              "formattedValue": "872.76K",
              "percentage": 1.02,
              "countryEmoji": "吼"
            },
            {
              "name": "Datadog Inc",
              "value": 0.0008,
              "formattedValue": "847.56K",
              "percentage": 0.99,
              "countryEmoji": ""
            },
            {
              "name": "Trimble Inc",
              "value": 0.0008,
              "formattedValue": "827.47K",
              "percentage": 0.97,
              "countryEmoji": "吼"
            },
            {
              "name": "Cooper Cos Inc",
              "value": 0.0008,
              "formattedValue": "794.07K",
              "percentage": 0.93,
              "countryEmoji": "吼"
            },
            {
              "name": "Analog Devices Inc",
              "value": 0.0008,
              "formattedValue": "790.48K",
              "percentage": 0.93,
              "countryEmoji": "吼"
            },
            {
              "name": "Honeywell International Inc",
              "value": 0.0008,
              "formattedValue": "778.82K",
              "percentage": 0.91,
              "countryEmoji": "吼"
            },
            {
              "name": "Amadeus IT Group SA",
              "value": 0.0008,
              "formattedValue": "777.50K",
              "percentage": 0.91,
              "countryEmoji": ""
            }
          ],
          [
            {
              "name": "London Stock Exchange Group",
              "value": 0.0008,
              "formattedValue": "772.88K",
              "percentage": 0.91,
              "countryEmoji": ""
            },
            {
              "name": "拽住 驻专",
              "value": 0.0008,
              "formattedValue": "770.02K",
              "percentage": 0.9,
              "countryEmoji": ""
            },
            {
              "name": "Kubota Corp",
              "value": 0.0007,
              "formattedValue": "749.53K",
              "percentage": 0.88,
              "countryEmoji": ""
            },
            {
              "name": "驻拽住",
              "value": 0.0006,
              "formattedValue": "640.86K",
              "percentage": 0.75,
              "countryEmoji": ""
            },
            {
              "name": "NEC Corp",
              "value": 0.0006,
              "formattedValue": "639.06K",
              "percentage": 0.75,
              "countryEmoji": ""
            },
            {
              "name": "拽 专",
              "value": 0.0006,
              "formattedValue": "599.14K",
              "percentage": 0.7,
              "countryEmoji": ""
            },
            {
              "name": "驻 专",
              "value": 0.0006,
              "formattedValue": "571.29K",
              "percentage": 0.67,
              "countryEmoji": ""
            },
            {
              "name": "Mitsui Fudosan Co Ltd",
              "value": 0.0006,
              "formattedValue": "568.33K",
              "percentage": 0.67,
              "countryEmoji": ""
            },
            {
              "name": "Haleon PLC",
              "value": 0.0006,
              "formattedValue": "566.39K",
              "percentage": 0.66,
              "countryEmoji": ""
            },
            {
              "name": ".住.",
              "value": 0.0005,
              "formattedValue": "537.78K",
              "percentage": 0.63,
              "countryEmoji": ""
            }
          ],
          [
            {
              "name": "KDDI Corp",
              "value": 0.0005,
              "formattedValue": "499.79K",
              "percentage": 0.59,
              "countryEmoji": ""
            },
            {
              "name": "LGI Homes Inc",
              "value": 0.0004,
              "formattedValue": "425.48K",
              "percentage": 0.5,
              "countryEmoji": "吼"
            },
            {
              "name": "专 1",
              "value": 0.0004,
              "formattedValue": "398.32K",
              "percentage": 0.47,
              "countryEmoji": ""
            },
            {
              "name": "注拽 驻住",
              "value": 0.0004,
              "formattedValue": "390.69K",
              "percentage": 0.46,
              "countryEmoji": ""
            },
            {
              "name": "'住",
              "value": 0.0004,
              "formattedValue": "380.59K",
              "percentage": 0.45,
              "countryEmoji": ""
            },
            {
              "name": "Rakuten Group Inc",
              "value": 0.0003,
              "formattedValue": "285.59K",
              "percentage": 0.33,
              "countryEmoji": ""
            },
            {
              "name": "住",
              "value": 0.0002,
              "formattedValue": "238.22K",
              "percentage": 0.28,
              "countryEmoji": ""
            },
            {
              "name": "住 驻专 砖",
              "value": 0.0002,
              "formattedValue": "222.14K",
              "percentage": 0.26,
              "countryEmoji": ""
            },
            {
              "name": "Upstream Bio Inc",
              "value": 0.0002,
              "formattedValue": "214.35K",
              "percentage": 0.25,
              "countryEmoji": "吼"
            },
            {
              "name": " 转 砖拽",
              "value": 0.0002,
              "formattedValue": "186.09K",
              "percentage": 0.22,
              "countryEmoji": ""
            }
          ],
          [
            {
              "name": "Tradeweb Markets Inc",
              "value": 0.0002,
              "formattedValue": "182.99K",
              "percentage": 0.21,
              "countryEmoji": ""
            },
            {
              "name": "Mowi ASA",
              "value": 0.0002,
              "formattedValue": "168.32K",
              "percentage": 0.2,
              "countryEmoji": "仇"
            },
            {
              "name": "驻专",
              "value": 0.0002,
              "formattedValue": "151.00K",
              "percentage": 0.18,
              "countryEmoji": ""
            },
            {
              "name": "Etoro Group Ltd",
              "value": 0.0001,
              "formattedValue": "107.02K",
              "percentage": 0.13,
              "countryEmoji": ""
            },
            {
              "name": "专 砖专",
              "value": 0.0001,
              "formattedValue": "88.91K",
              "percentage": 0.1,
              "countryEmoji": ""
            },
            {
              "name": "住 驻住",
              "value": 0.0001,
              "formattedValue": "87.10K",
              "percentage": 0.1,
              "countryEmoji": ""
            },
            {
              "name": "砖 住",
              "value": 0.0001,
              "formattedValue": "83.08K",
              "percentage": 0.1,
              "countryEmoji": ""
            },
            {
              "name": " 转注砖转",
              "value": 0.0001,
              "formattedValue": "63.40K",
              "percentage": 0.07,
              "countryEmoji": ""
            },
            {
              "name": "PennantPark Floating Rate Capi",
              "value": 0.0001,
              "formattedValue": "62.69K",
              "percentage": 0.07,
              "countryEmoji": "吼"
            },
            {
              "name": "专 拽专驻",
              "value": 0.0001,
              "formattedValue": "59.12K",
              "percentage": 0.07,
              "countryEmoji": ""
            }
          ],
          [
            {
              "name": "Oddity Tech Ltd",
              "value": 0.0,
              "formattedValue": "44.31K",
              "percentage": 0.05,
              "countryEmoji": "吼"
            },
            {
              "name": "专 砖拽 ",
              "value": 0.0,
              "formattedValue": "42.66K",
              "percentage": 0.05,
              "countryEmoji": ""
            },
            {
              "name": "住住",
              "value": 0.0,
              "formattedValue": "38.99K",
              "percentage": 0.05,
              "countryEmoji": ""
            },
            {
              "name": "专'拽住",
              "value": 0.0,
              "formattedValue": "22.62K",
              "percentage": 0.03,
              "countryEmoji": ""
            },
            {
              "name": "注拽 拽爪",
              "value": 0.0,
              "formattedValue": "11.83K",
              "percentage": 0.01,
              "countryEmoji": ""
            },
            {
              "name": "专住 ",
              "value": 0.0,
              "formattedValue": "3.72K",
              "percentage": 0.0,
              "countryEmoji": ""
            },
            {
              "name": "Mobilicom Ltd",
              "value": 0.0,
              "formattedValue": "1.70K",
              "percentage": 0.0,
              "countryEmoji": ""
            }
          ]
        ]
      },
      {
        "subclass": "ETFs",
        "value": 0.0086,
        "formattedValue": "8.62M",
        "percentageOfClass": 9.18,
        "itemCount": 22,
        "totalPages": 3,
        "holdingsPages": [
          [
            {
              "name": "Amundi Stoxx Europe 600 UCITS",
              "value": 0.0038,
              "formattedValue": "3.82M",
              "percentage": 44.3,
              "countryEmoji": ""
            },
            {
              "name": "Energy Select Sector SPDR Fund",
              "value": 0.0017,
              "formattedValue": "1.70M",
              "percentage": 19.75,
              "countryEmoji": "吼"
            },
            {
              "name": "Global X Copper Miners ETF",
              "value": 0.0015,
              "formattedValue": "1.51M",
              "percentage": 17.51,
              "countryEmoji": ""
            },
            {
              "name": "Amundi Stoxx Europe 600 Banks",
              "value": 0.001,
              "formattedValue": "997.31K",
              "percentage": 11.56,
              "countryEmoji": ""
            },
            {
              "name": "Health Care Select Sector SPDR",
              "value": 0.0005,
              "formattedValue": "539.42K",
              "percentage": 6.25,
              "countryEmoji": "吼"
            },
            {
              "name": "Invesco QQQ Trust Series 1",
              "value": 0.0,
              "formattedValue": "38.22K",
              "percentage": 0.44,
              "countryEmoji": "吼"
            },
            {
              "name": "SPDR S&P 500 ETF Trust",
              "value": 0.0,
              "formattedValue": "7.99K",
              "percentage": 0.09,
              "countryEmoji": "吼"
            },
            {
              "name": "MTF 住 Nasdaq 100",
              "value": 0.0,
              "formattedValue": "2.72K",
              "percentage": 0.03,
              "countryEmoji": "吼"
            },
            {
              "name": "专 住  S&P 500",
              "value": 0.0,
              "formattedValue": "0.80K",
              "percentage": 0.01,
              "countryEmoji": "吼"
            },
            {
              "name": "NEXT FUNDS TOPIX Exchange Trad",
              "value": 0.0,
              "formattedValue": "0.75K",
              "percentage": 0.01,
              "countryEmoji": ""
            }
          ],
          [
            {
              "name": "专 住  NASDAQ 100",
              "value": 0.0,
              "formattedValue": "0.70K",
              "percentage": 0.01,
              "countryEmoji": "吼"
            },
            {
              "name": "转转 住 NASDAQ 100",
              "value": 0.0,
              "formattedValue": "0.60K",
              "percentage": 0.01,
              "countryEmoji": "吼"
            },
            {
              "name": "转转 住  STOXX Europe 600",
              "value": 0.0,
              "formattedValue": "0.45K",
              "percentage": 0.01,
              "countryEmoji": ""
            },
            {
              "name": "Invesco STOXX Europe 600 UCITS",
              "value": 0.0,
              "formattedValue": "0.23K",
              "percentage": 0.0,
              "countryEmoji": ""
            },
            {
              "name": "iShares Core S&P 500 ETF",
              "value": 0.0,
              "formattedValue": "0.21K",
              "percentage": 0.0,
              "countryEmoji": "吼"
            },
            {
              "name": "Vanguard S&P 500 ETF",
              "value": 0.0,
              "formattedValue": "0.21K",
              "percentage": 0.0,
              "countryEmoji": "吼"
            },
            {
              "name": "VanEck Semiconductor ETF",
              "value": 0.0,
              "formattedValue": "0.19K",
              "percentage": 0.0,
              "countryEmoji": "吼"
            },
            {
              "name": "First Trust NASDAQ Clean Edge",
              "value": 0.0,
              "formattedValue": "0.18K",
              "percentage": 0.0,
              "countryEmoji": ""
            },
            {
              "name": "iFree ETF-Nikkei 225",
              "value": 0.0,
              "formattedValue": "0.15K",
              "percentage": 0.0,
              "countryEmoji": ""
            },
            {
              "name": "拽住 NASDAQ 100 ETF",
              "value": 0.0,
              "formattedValue": "0.10K",
              "percentage": 0.0,
              "countryEmoji": "吼"
            }
          ],
          [
            {
              "name": "iShares Global Energy ETF",
              "value": 0.0,
              "formattedValue": "0.02K",
              "percentage": 0.0,
              "countryEmoji": ""
            },
            {
              "name": "INVESCO KBW BANK ETF",
              "value": 0.0,
              "formattedValue": "0.02K",
              "percentage": 0.0,
              "countryEmoji": "吼"
            }
          ]
        ]
      }
    ],
    "Investment Funds": [
      {
        "subclass": "Funds",
        "value": 0.0037,
        "formattedValue": "3.65M",
        "percentageOfClass": 100.0,
        "itemCount": 32,
        "totalPages": 4,
        "holdingsPages": [
          [
            {
              "name": "Accolade Partners 8-F Feeder (Kleiner Perkins)",
              "value": 0.0004,
              "formattedValue": "378.32K",
              "percentage": 10.36,
              "countryEmoji": "吼"
            },
            {
              "name": "Hyperwise Ventures Fund 2",
              "value": 0.0004,
              "formattedValue": "356.72K",
              "percentage": 9.77,
              "countryEmoji": ""
            },
            {
              "name": "Lightspeed opportunity 2",
              "value": 0.0003,
              "formattedValue": "256.41K",
              "percentage": 7.02,
              "countryEmoji": ""
            },
            {
              "name": "Thoma Bravo Discover 4",
              "value": 0.0002,
              "formattedValue": "248.11K",
              "percentage": 6.8,
              "countryEmoji": "吼"
            },
            {
              "name": "AP PARTNERS 2",
              "value": 0.0002,
              "formattedValue": "228.39K",
              "percentage": 6.26,
              "countryEmoji": ""
            },
            {
              "name": "Klirmark Opportunity Fund 4",
              "value": 0.0002,
              "formattedValue": "225.73K",
              "percentage": 6.18,
              "countryEmoji": ""
            },
            {
              "name": "AP Partners II Soglowek L.P.",
              "value": 0.0002,
              "formattedValue": "187.51K",
              "percentage": 5.14,
              "countryEmoji": ""
            },
            {
              "name": "Francisco Partners VII[-A] L.P",
              "value": 0.0002,
              "formattedValue": "157.63K",
              "percentage": 4.32,
              "countryEmoji": "吼"
            },
            {
              "name": "FORTISSIMO 6",
              "value": 0.0002,
              "formattedValue": "152.50K",
              "percentage": 4.18,
              "countryEmoji": ""
            },
            {
              "name": "Aurum",
              "value": 0.0002,
              "formattedValue": "150.19K",
              "percentage": 4.11,
              "countryEmoji": ""
            }
          ],
          [
            {
              "name": "Brosh Capital new",
              "value": 0.0001,
              "formattedValue": "126.44K",
              "percentage": 3.46,
              "countryEmoji": ""
            },
            {
              "name": "Entree Early Growth 2",
              "value": 0.0001,
              "formattedValue": "115.58K",
              "percentage": 3.17,
              "countryEmoji": ""
            },
            {
              "name": "拽专 抓",
              "value": 0.0001,
              "formattedValue": "113.50K",
              "percentage": 3.11,
              "countryEmoji": ""
            },
            {
              "name": "Lightspeed select 5",
              "value": 0.0001,
              "formattedValue": "107.97K",
              "percentage": 2.96,
              "countryEmoji": ""
            },
            {
              "name": "ONE EQUITY IX",
              "value": 0.0001,
              "formattedValue": "101.31K",
              "percentage": 2.78,
              "countryEmoji": ""
            },
            {
              "name": "Israel Secondary Fund 3",
              "value": 0.0001,
              "formattedValue": "93.90K",
              "percentage": 2.57,
              "countryEmoji": ""
            },
            {
              "name": "专 ",
              "value": 0.0001,
              "formattedValue": "68.59K",
              "percentage": 1.88,
              "countryEmoji": ""
            },
            {
              "name": "Lightspeed XIV-B",
              "value": 0.0001,
              "formattedValue": "66.78K",
              "percentage": 1.83,
              "countryEmoji": "吼"
            },
            {
              "name": "Northwind Debt Fund 2 FEEDER D LP",
              "value": 0.0001,
              "formattedValue": "64.68K",
              "percentage": 1.77,
              "countryEmoji": "吼"
            },
            {
              "name": "Thoma Bravo Explore 2",
              "value": 0.0001,
              "formattedValue": "53.56K",
              "percentage": 1.47,
              "countryEmoji": "吼"
            }
          ],
          [
            {
              "name": "Northwind Debt Fund 2 FEEDER C LP",
              "value": 0.0001,
              "formattedValue": "53.01K",
              "percentage": 1.45,
              "countryEmoji": "吼"
            },
            {
              "name": "Lightspeed XIV-A",
              "value": 0.0001,
              "formattedValue": "52.16K",
              "percentage": 1.43,
              "countryEmoji": "吼"
            },
            {
              "name": "10D",
              "value": 0.0,
              "formattedValue": "47.99K",
              "percentage": 1.31,
              "countryEmoji": ""
            },
            {
              "name": "Entree Early Stage 4",
              "value": 0.0,
              "formattedValue": "47.21K",
              "percentage": 1.29,
              "countryEmoji": ""
            },
            {
              "name": "NORTHWIND HEALTHCARE DEBT FUND 1 FEEDER D LP",
              "value": 0.0,
              "formattedValue": "44.19K",
              "percentage": 1.21,
              "countryEmoji": "吼"
            },
            {
              "name": "BK Opportunities Fund 7",
              "value": 0.0,
              "formattedValue": "38.56K",
              "percentage": 1.06,
              "countryEmoji": ""
            },
            {
              "name": "CLARION 2",
              "value": 0.0,
              "formattedValue": "33.68K",
              "percentage": 0.92,
              "countryEmoji": "吼"
            },
            {
              "name": "NORTHWIND HEALTHCARE DEBT FUND 1 FEEDER C LP",
              "value": 0.0,
              "formattedValue": "26.52K",
              "percentage": 0.73,
              "countryEmoji": "吼"
            },
            {
              "name": "ZEEV Ventures 9",
              "value": 0.0,
              "formattedValue": "26.15K",
              "percentage": 0.72,
              "countryEmoji": ""
            },
            {
              "name": "KPS 6",
              "value": 0.0,
              "formattedValue": "13.87K",
              "percentage": 0.38,
              "countryEmoji": ""
            }
          ],
          [
            {
              "name": "FRANCISCO PARTNERS AGILITY III[-A] L.P",
              "value": 0.0,
              "formattedValue": "7.21K",
              "percentage": 0.2,
              "countryEmoji": "吼"
            },
            {
              "name": "Stage One Annex (Opportunity)",
              "value": 0.0,
              "formattedValue": "5.85K",
              "percentage": 0.16,
              "countryEmoji": ""
            }
          ]
        ]
      }
    ],
    "Warrants": [
      {
        "subclass": "Tradable",
        "value": 0.0001,
        "formattedValue": "68.72K",
        "percentageOfClass": 88.34,
        "itemCount": 23,
        "totalPages": 3,
        "holdingsPages": [
          [
            {
              "name": "拽住  驻 2",
              "value": 0.0,
              "formattedValue": "28.44K",
              "percentage": 41.39,
              "countryEmoji": ""
            },
            {
              "name": " 抓 驻 16",
              "value": 0.0,
              "formattedValue": "12.72K",
              "percentage": 18.5,
              "countryEmoji": ""
            },
            {
              "name": "Airship AI Holdings Inc",
              "value": 0.0,
              "formattedValue": "8.93K",
              "percentage": 13.0,
              "countryEmoji": "吼"
            },
            {
              "name": "住 驻 驻 6",
              "value": 0.0,
              "formattedValue": "7.59K",
              "percentage": 11.04,
              "countryEmoji": ""
            },
            {
              "name": "NioCorp Developments Ltd",
              "value": 0.0,
              "formattedValue": "6.66K",
              "percentage": 9.69,
              "countryEmoji": "吼"
            },
            {
              "name": "驻专  驻 1",
              "value": 0.0,
              "formattedValue": "2.09K",
              "percentage": 3.05,
              "countryEmoji": ""
            },
            {
              "name": "Falcon's Beyond Global Inc",
              "value": 0.0,
              "formattedValue": "0.70K",
              "percentage": 1.02,
              "countryEmoji": "吼"
            },
            {
              "name": "Satellogic Inc",
              "value": 0.0,
              "formattedValue": "0.46K",
              "percentage": 0.66,
              "countryEmoji": "吼"
            },
            {
              "name": "Classover Holdings Inc",
              "value": 0.0,
              "formattedValue": "0.31K",
              "percentage": 0.46,
              "countryEmoji": "吼"
            },
            {
              "name": "ECARX Holdings Inc",
              "value": 0.0,
              "formattedValue": "0.29K",
              "percentage": 0.42,
              "countryEmoji": ""
            }
          ],
          [
            {
              "name": "EVe Mobility Acquisition Corp",
              "value": 0.0,
              "formattedValue": "0.13K",
              "percentage": 0.19,
              "countryEmoji": "吼"
            },
            {
              "name": "Taboola.com Ltd",
              "value": 0.0,
              "formattedValue": "0.12K",
              "percentage": 0.18,
              "countryEmoji": ""
            },
            {
              "name": "Athena Technology Acquisition",
              "value": 0.0,
              "formattedValue": "0.09K",
              "percentage": 0.13,
              "countryEmoji": "吼"
            },
            {
              "name": "Veea Inc",
              "value": 0.0,
              "formattedValue": "0.05K",
              "percentage": 0.08,
              "countryEmoji": "吼"
            },
            {
              "name": "Ginkgo Bioworks Holdings Inc",
              "value": 0.0,
              "formattedValue": "0.03K",
              "percentage": 0.05,
              "countryEmoji": "吼"
            },
            {
              "name": "Investcorp Europe Acquisition",
              "value": 0.0,
              "formattedValue": "0.02K",
              "percentage": 0.03,
              "countryEmoji": "吼"
            },
            {
              "name": "Abpro Holdings Inc",
              "value": 0.0,
              "formattedValue": "0.02K",
              "percentage": 0.03,
              "countryEmoji": "吼"
            },
            {
              "name": "Terran Orbital Corp",
              "value": 0.0,
              "formattedValue": "0.02K",
              "percentage": 0.03,
              "countryEmoji": "吼"
            },
            {
              "name": "Papaya Growth Opportunity Corp",
              "value": 0.0,
              "formattedValue": "0.01K",
              "percentage": 0.01,
              "countryEmoji": "吼"
            },
            {
              "name": "Jaws Mustang Acquisition Corp",
              "value": 0.0,
              "formattedValue": "0.01K",
              "percentage": 0.01,
              "countryEmoji": "吼"
            }
          ],
          [
            {
              "name": "Brand Engagement Network Inc",
              "value": 0.0,
              "formattedValue": "0.01K",
              "percentage": 0.01,
              "countryEmoji": "吼"
            },
            {
              "name": "Slam Corp",
              "value": 0.0,
              "formattedValue": "0.01K",
              "percentage": 0.01,
              "countryEmoji": "吼"
            },
            {
              "name": "Heliogen Inc",
              "value": 0.0,
              "formattedValue": "0.00K",
              "percentage": 0.01,
              "countryEmoji": "吼"
            }
          ]
        ]
      },
      {
        "subclass": "Non-Tradable",
        "value": 0.0,
        "formattedValue": "9.07K",
        "percentageOfClass": 11.66,
        "itemCount": 1,
        "totalPages": 1,
        "holdingsPages": [
          [
            {
              "name": "驻 专 - 驻爪  住专 31.01.2026",
              "value": 0.0,
              "formattedValue": "9.07K",
              "percentage": 100.0,
              "countryEmoji": ""
            }
          ]
        ]
      }
    ],
    "Derivatives": [
      {
        "subclass": "General",
        "value": 0.0017,
        "formattedValue": "1.75M",
        "percentageOfClass": 100.0,
        "itemCount": 13,
        "totalPages": 2,
        "holdingsPages": [
          [
            {
              "name": "2330 TT EQUITY",
              "value": 0.0007,
              "formattedValue": "656.51K",
              "percentage": 37.52,
              "countryEmoji": "吼"
            },
            {
              "name": "USDILS",
              "value": 0.0006,
              "formattedValue": "588.59K",
              "percentage": 33.64,
              "countryEmoji": "吼"
            },
            {
              "name": "CGASASSA INDEX",
              "value": 0.0004,
              "formattedValue": "386.45K",
              "percentage": 22.09,
              "countryEmoji": "吼"
            },
            {
              "name": "GSALTEPW INDEX",
              "value": 0.0002,
              "formattedValue": "169.39K",
              "percentage": 9.68,
              "countryEmoji": ""
            },
            {
              "name": "GSALTPOW INDEX",
              "value": 0.0001,
              "formattedValue": "88.26K",
              "percentage": 5.04,
              "countryEmoji": "吼"
            },
            {
              "name": "IXVTR INDEX",
              "value": -0.0,
              "formattedValue": "-43.27K",
              "percentage": -2.47,
              "countryEmoji": "吼"
            },
            {
              "name": "EURILS",
              "value": -0.0,
              "formattedValue": "-29.79K",
              "percentage": -1.7,
              "countryEmoji": ""
            },
            {
              "name": "USDJPY",
              "value": -0.0,
              "formattedValue": "-28.94K",
              "percentage": -1.65,
              "countryEmoji": "吼"
            },
            {
              "name": "NOKILS",
              "value": -0.0,
              "formattedValue": "-23.21K",
              "percentage": -1.33,
              "countryEmoji": "仇"
            },
            {
              "name": "EURUSD",
              "value": -0.0,
              "formattedValue": "-9.65K",
              "percentage": -0.55,
              "countryEmoji": ""
            }
          ],
          [
            {
              "name": "USDCAD",
              "value": -0.0,
              "formattedValue": "-9.32K",
              "percentage": -0.53,
              "countryEmoji": "吼"
            },
            {
              "name": "SX7GR INDEX",
              "value": 0.0,
              "formattedValue": "4.79K",
              "percentage": 0.27,
              "countryEmoji": ""
            },
            {
              "name": " 转\" 90",
              "value": 0.0,
              "formattedValue": "0.02K",
              "percentage": 0.0,
              "countryEmoji": ""
            }
          ]
        ]
      }
    ],
    "Mutual Funds": [
      {
        "subclass": "General",
        "value": 0.0067,
        "formattedValue": "6.74M",
        "percentageOfClass": 100.0,
        "itemCount": 11,
        "totalPages": 2,
        "holdingsPages": [
          [
            {
              "name": "ARTEMIS UK SELECT FUND-INS A",
              "value": 0.002,
              "formattedValue": "1.95M",
              "percentage": 28.97,
              "countryEmoji": ""
            },
            {
              "name": "Kotak Funds - India Midcap Fun",
              "value": 0.0007,
              "formattedValue": "744.57K",
              "percentage": 11.04,
              "countryEmoji": ""
            },
            {
              "name": "Ashoka WhiteOak ICAV - Ashoka",
              "value": 0.0007,
              "formattedValue": "724.73K",
              "percentage": 10.75,
              "countryEmoji": ""
            },
            {
              "name": "Liontrust European Dynamic Fun",
              "value": 0.0007,
              "formattedValue": "709.42K",
              "percentage": 10.52,
              "countryEmoji": ""
            },
            {
              "name": "TRIGON - New Europe Fund/Luxem",
              "value": 0.0006,
              "formattedValue": "573.44K",
              "percentage": 8.5,
              "countryEmoji": ""
            },
            {
              "name": "Nomura Funds Ireland - India E",
              "value": 0.0005,
              "formattedValue": "506.99K",
              "percentage": 7.52,
              "countryEmoji": ""
            },
            {
              "name": "LAZARD JAPA STRA EQIT-J ACCJ",
              "value": 0.0005,
              "formattedValue": "488.22K",
              "percentage": 7.24,
              "countryEmoji": ""
            },
            {
              "name": "HBM Healthcare Investments AG",
              "value": 0.0005,
              "formattedValue": "452.38K",
              "percentage": 6.71,
              "countryEmoji": ""
            },
            {
              "name": "VisionFund - Japan Equity Valu",
              "value": 0.0003,
              "formattedValue": "250.77K",
              "percentage": 3.72,
              "countryEmoji": ""
            },
            {
              "name": "Arcus SICAV Fund Arcus Japan F",
              "value": 0.0002,
              "formattedValue": "248.49K",
              "percentage": 3.68,
              "countryEmoji": ""
            }
          ],
          [
            {
              "name": "Goehring & Rozencwajg Resource",
              "value": 0.0001,
              "formattedValue": "91.09K",
              "percentage": 1.35,
              "countryEmoji": ""
            }
          ]
        ]
      }
    ],
    "Futures": [
      {
        "subclass": "General",
        "value": 0.0013,
        "formattedValue": "1.32M",
        "percentageOfClass": 100.0,
        "itemCount": 4,
        "totalPages": 1,
        "holdingsPages": [
          [
            {
              "name": "NASDAQ 100 E-MINI Dec25",
              "value": 0.0012,
              "formattedValue": "1.15M",
              "percentage": 87.05,
              "countryEmoji": ""
            },
            {
              "name": "NIKKEI 225 (OSE) DEC25",
              "value": 0.0001,
              "formattedValue": "142.40K",
              "percentage": 10.76,
              "countryEmoji": ""
            },
            {
              "name": "TOPIX INDX FUTR Dec25",
              "value": 0.0,
              "formattedValue": "27.58K",
              "percentage": 2.08,
              "countryEmoji": ""
            },
            {
              "name": "S&P500 EMINI FUT DEC25",
              "value": 0.0,
              "formattedValue": "1.38K",
              "percentage": 0.1,
              "countryEmoji": ""
            }
          ]
        ]
      }
    ]
  },
  "geoSunburst": [
    {
      "name": "Israel",
      "value": 0.1512,
      "formattedValue": "151.22M",
      "children": [
        {
          "name": "Cash & Equivalents",
          "value": 0.0627,
          "formattedValue": "62.74M"
        },
        {
          "name": "Bonds",
          "value": 0.0491,
          "formattedValue": "49.14M"
        },
        {
          "name": "Stocks",
          "value": 0.0357,
          "formattedValue": "35.70M"
        },
        {
          "name": "Investment Funds",
          "value": 0.0016,
          "formattedValue": "1.61M"
        },
        {
          "name": "Other Assets",
          "value": 0.001,
          "formattedValue": "991.11K"
        },
        {
          "name": "Non-Tradable Stocks",
          "value": 0.0007,
          "formattedValue": "718.71K"
        },
        {
          "name": "Derivatives",
          "value": 0.0003,
          "formattedValue": "317.06K"
        }
      ]
    },
    {
      "name": "USA",
      "value": 0.0587,
      "formattedValue": "58.66M",
      "children": [
        {
          "name": "Stocks",
          "value": 0.0358,
          "formattedValue": "35.78M"
        },
        {
          "name": "Bonds",
          "value": 0.0157,
          "formattedValue": "15.66M"
        },
        {
          "name": "Options",
          "value": 0.0038,
          "formattedValue": "3.79M"
        },
        {
          "name": "Derivatives",
          "value": 0.0022,
          "formattedValue": "2.24M"
        },
        {
          "name": "Investment Funds",
          "value": 0.0012,
          "formattedValue": "1.19M"
        }
      ]
    },
    {
      "name": "Global",
      "value": 0.0137,
      "formattedValue": "13.74M",
      "children": [
        {
          "name": "Stocks",
          "value": 0.0099,
          "formattedValue": "9.91M"
        },
        {
          "name": "Options",
          "value": 0.0016,
          "formattedValue": "1.65M"
        },
        {
          "name": "Futures",
          "value": 0.0013,
          "formattedValue": "1.32M"
        },
        {
          "name": "Investment Funds",
          "value": 0.0009,
          "formattedValue": "857.25K"
        }
      ]
    },
    {
      "name": "Eurozone",
      "value": 0.0061,
      "formattedValue": "6.10M",
      "children": [
        {
          "name": "Stocks",
          "value": 0.0048,
          "formattedValue": "4.82M"
        },
        {
          "name": "Mutual Funds",
          "value": 0.0013,
          "formattedValue": "1.28M"
        }
      ]
    },
    {
      "name": "UK",
      "value": 0.0035,
      "formattedValue": "3.53M",
      "children": [
        {
          "name": "Mutual Funds",
          "value": 0.002,
          "formattedValue": "1.95M"
        },
        {
          "name": "Stocks",
          "value": 0.0016,
          "formattedValue": "1.57M"
        }
      ]
    },
    {
      "name": "Japan",
      "value": 0.003,
      "formattedValue": "2.98M",
      "children": [
        {
          "name": "Stocks",
          "value": 0.002,
          "formattedValue": "1.99M"
        },
        {
          "name": "Mutual Funds",
          "value": 0.001,
          "formattedValue": "987.48K"
        }
      ]
    },
    {
      "name": "India",
      "value": 0.002,
      "formattedValue": "1.98M",
      "children": [
        {
          "name": "Mutual Funds",
          "value": 0.002,
          "formattedValue": "1.98M"
        }
      ]
    },
    {
      "name": "France",
      "value": 0.0013,
      "formattedValue": "1.28M",
      "children": [
        {
          "name": "Stocks",
          "value": 0.0013,
          "formattedValue": "1.28M"
        }
      ]
    },
    {
      "name": "Canada",
      "value": 0.001,
      "formattedValue": "1.01M",
      "children": [
        {
          "name": "Stocks",
          "value": 0.001,
          "formattedValue": "1.01M"
        }
      ]
    },
    {
      "name": "Netherlands",
      "value": 0.0009,
      "formattedValue": "918.24K",
      "children": [
        {
          "name": "Stocks",
          "value": 0.0009,
          "formattedValue": "918.24K"
        }
      ]
    },
    {
      "name": "Spain",
      "value": 0.0008,
      "formattedValue": "777.50K",
      "children": [
        {
          "name": "Stocks",
          "value": 0.0008,
          "formattedValue": "777.50K"
        }
      ]
    },
    {
      "name": "Switzerland",
      "value": 0.0005,
      "formattedValue": "452.38K",
      "children": [
        {
          "name": "Mutual Funds",
          "value": 0.0005,
          "formattedValue": "452.38K"
        }
      ]
    },
    {
      "name": "Norway",
      "value": 0.0002,
      "formattedValue": "168.32K",
      "children": [
        {
          "name": "Stocks",
          "value": 0.0002,
          "formattedValue": "168.32K"
        }
      ]
    }
  ],
  "currencySunburst": [
    {
      "name": "ILS",
      "value": 0.1303,
      "formattedValue": "130.29M",
      "children": [
        {
          "name": "Bonds",
          "value": 0.0491,
          "formattedValue": "49.14M"
        },
        {
          "name": "Cash & Equivalents",
          "value": 0.0422,
          "formattedValue": "42.19M"
        },
        {
          "name": "Stocks",
          "value": 0.0358,
          "formattedValue": "35.77M"
        },
        {
          "name": "Other Assets",
          "value": 0.001,
          "formattedValue": "991.11K"
        },
        {
          "name": "Investment Funds",
          "value": 0.0008,
          "formattedValue": "836.67K"
        },
        {
          "name": "Non-Tradable Stocks",
          "value": 0.0007,
          "formattedValue": "718.71K"
        },
        {
          "name": "Mutual Funds",
          "value": 0.0005,
          "formattedValue": "452.38K"
        },
        {
          "name": "Derivatives",
          "value": 0.0002,
          "formattedValue": "197.42K"
        }
      ]
    },
    {
      "name": "USD",
      "value": 0.0931,
      "formattedValue": "93.14M",
      "children": [
        {
          "name": "Stocks",
          "value": 0.0458,
          "formattedValue": "45.78M"
        },
        {
          "name": "Cash & Equivalents",
          "value": 0.0185,
          "formattedValue": "18.50M"
        },
        {
          "name": "Bonds",
          "value": 0.0157,
          "formattedValue": "15.66M"
        },
        {
          "name": "Options",
          "value": 0.0049,
          "formattedValue": "4.94M"
        },
        {
          "name": "Investment Funds",
          "value": 0.0028,
          "formattedValue": "2.77M"
        },
        {
          "name": "Derivatives",
          "value": 0.0023,
          "formattedValue": "2.26M"
        },
        {
          "name": "Mutual Funds",
          "value": 0.0021,
          "formattedValue": "2.07M"
        },
        {
          "name": "Futures",
          "value": 0.0012,
          "formattedValue": "1.15M"
        }
      ]
    },
    {
      "name": "EUR",
      "value": 0.0102,
      "formattedValue": "10.18M",
      "children": [
        {
          "name": "Stocks",
          "value": 0.0078,
          "formattedValue": "7.79M"
        },
        {
          "name": "Cash & Equivalents",
          "value": 0.0017,
          "formattedValue": "1.69M"
        },
        {
          "name": "Mutual Funds",
          "value": 0.0006,
          "formattedValue": "573.44K"
        },
        {
          "name": "Derivatives",
          "value": 0.0001,
          "formattedValue": "130.17K"
        }
      ]
    },
    {
      "name": "JPY",
      "value": 0.0058,
      "formattedValue": "5.84M",
      "children": [
        {
          "name": "Stocks",
          "value": 0.0038,
          "formattedValue": "3.82M"
        },
        {
          "name": "Mutual Funds",
          "value": 0.001,
          "formattedValue": "987.48K"
        },
        {
          "name": "Options",
          "value": 0.0005,
          "formattedValue": "497.48K"
        },
        {
          "name": "Cash & Equivalents",
          "value": 0.0004,
          "formattedValue": "359.31K"
        },
        {
          "name": "Futures",
          "value": 0.0002,
          "formattedValue": "169.98K"
        }
      ]
    },
    {
      "name": "GBP",
      "value": 0.0034,
      "formattedValue": "3.44M",
      "children": [
        {
          "name": "Mutual Funds",
          "value": 0.0027,
          "formattedValue": "2.66M"
        },
        {
          "name": "Stocks",
          "value": 0.0008,
          "formattedValue": "772.88K"
        }
      ]
    }
  ]
}